PyWinSevice/WinService.py
PyWinSevice/__init__.py
WinService-0.0.1.dist-info/LICENSE
WinService-0.0.1.dist-info/METADATA
WinService-0.0.1.dist-info/WHEEL
WinService-0.0.1.dist-info/top_level.txt
WinService-0.0.1.dist-info/RECORD
