Metadata-Version: 2.1
Name: WinService
Version: 0.0.1
Summary: Package to manage windows service
Home-page: https://github.com/Prastiwar/PyWinService
Author: Tomasz Piowczyk
Author-email: tomasz.piowczyk@gmail.com
License: UNKNOWN
Platform: UNKNOWN
Classifier: Programming Language :: Python :: 3
Classifier: License :: OSI Approved :: MIT License
Classifier: Operating System :: Microsoft :: Windows
